spotify_confidence/__init__.py
spotify_confidence/chartgrid.py
spotify_confidence/examples.py
spotify_confidence/options.py
spotify_confidence/analysis/__init__.py
spotify_confidence/analysis/confidence_utils.py
spotify_confidence/analysis/constants.py
spotify_confidence/analysis/abstract_base_classes/__init__.py
spotify_confidence/analysis/abstract_base_classes/confidence_abc.py
spotify_confidence/analysis/abstract_base_classes/confidence_computer_abc.py
spotify_confidence/analysis/abstract_base_classes/confidence_grapher_abc.py
spotify_confidence/analysis/bayesian/__init__.py
spotify_confidence/analysis/bayesian/bayesian_base.py
spotify_confidence/analysis/bayesian/bayesian_models.py
spotify_confidence/analysis/frequentist/__init__.py
spotify_confidence/analysis/frequentist/chartify_grapher.py
spotify_confidence/analysis/frequentist/chi_squared.py
spotify_confidence/analysis/frequentist/experiment.py
spotify_confidence/analysis/frequentist/multiple_comparison.py
spotify_confidence/analysis/frequentist/nims_and_mdes.py
spotify_confidence/analysis/frequentist/sample_ratio_test.py
spotify_confidence/analysis/frequentist/sample_size_calculator.py
spotify_confidence/analysis/frequentist/sequential_bound_solver.py
spotify_confidence/analysis/frequentist/t_test.py
spotify_confidence/analysis/frequentist/z_test.py
spotify_confidence/analysis/frequentist/z_test_linreg.py
spotify_confidence/analysis/frequentist/confidence_computers/__init__.py
spotify_confidence/analysis/frequentist/confidence_computers/bootstrap_computer.py
spotify_confidence/analysis/frequentist/confidence_computers/chi_squared_computer.py
spotify_confidence/analysis/frequentist/confidence_computers/confidence_computer.py
spotify_confidence/analysis/frequentist/confidence_computers/sample_size_computer.py
spotify_confidence/analysis/frequentist/confidence_computers/t_test_computer.py
spotify_confidence/analysis/frequentist/confidence_computers/z_test_computer.py
spotify_confidence-4.0.0.dist-info/AUTHORS.md
spotify_confidence-4.0.0.dist-info/LICENSE
spotify_confidence-4.0.0.dist-info/METADATA
spotify_confidence-4.0.0.dist-info/WHEEL
spotify_confidence-4.0.0.dist-info/top_level.txt
spotify_confidence-4.0.0.dist-info/RECORD
