Metadata-Version: 2.1
Name: spotify-confidence
Version: 4.0.0
Summary: Package for calculating and visualising confidence intervals, e.g. for A/B test analysis.
Home-page: https://github.com/spotify/confidence
Author: Per Sillren
Author-email: pers@spotify.com
Project-URL: Bug Tracker, https://github.com/spotify/confidence/issues
Classifier: Programming Language :: Python :: 3
Classifier: License :: OSI Approved :: Apache Software License
Classifier: Operating System :: OS Independent
Requires-Python: >=3.9
License-File: LICENSE
License-File: AUTHORS.md
Requires-Dist: numpy<2.0.0,>=1.20.0
Requires-Dist: scipy>=1.6.0
Requires-Dist: pandas>=1.2.0
Requires-Dist: statsmodels<1.0.0,>=0.13.0
Requires-Dist: chartify>=5.0.1
Requires-Dist: ipywidgets>=8.0.0
